deeptables/__init__.py
deeptables/_version.py
deeptables/datasets/__init__.py
deeptables/eda/__init__.py
deeptables/eda/utils.py
deeptables/examples/Kaggle - Categorical Feature Encoding Challenge II.ipynb
deeptables/examples/__init__.py
deeptables/examples/automl.ipynb
deeptables/examples/dt_cross_validation.ipynb
deeptables/examples/dt_multiclass.ipynb
deeptables/examples/dt_regression.ipynb
deeptables/examples/extract_layer_outputs.ipynb
deeptables/examples/model_explaination_shap.ipynb
deeptables/examples/quickstart.ipynb
deeptables/examples/readme.ipynb
deeptables/fe/__init__.py
deeptables/fe/dae.py
deeptables/models/__init__.py
deeptables/models/config.py
deeptables/models/deepmodel.py
deeptables/models/deepnets.py
deeptables/models/deeptable.py
deeptables/models/hyper_dt.py
deeptables/models/layers.py
deeptables/models/metainfo.py
deeptables/models/modelset.py
deeptables/models/preprocessor.py
deeptables/preprocessing/__init__.py
deeptables/preprocessing/utils.py
deeptables/tests/__init__.py
deeptables/tests/misc.py
deeptables/tests/models/__init__.py
deeptables/tests/models/config_test.py
deeptables/tests/models/deepmodel_test.py
deeptables/tests/models/deeptable_callback_test.py
deeptables/tests/models/deeptable_cv_test.py
deeptables/tests/models/deeptable_dask_test.py
deeptables/tests/models/deeptable_multiclass_test.py
deeptables/tests/models/deeptable_multilabel_test.py
deeptables/tests/models/deeptable_regression_test.py
deeptables/tests/models/deeptable_test.py
deeptables/tests/models/hyper_dt_experiment_test.py
deeptables/tests/models/hyper_dt_regression_test.py
deeptables/tests/models/hyper_dt_test.py
deeptables/tests/models/layers_test.py
deeptables/tests/models/model_input_test.py
deeptables/tests/models/modelset_test.py
deeptables/tests/models/multi_classification.py
deeptables/tests/models/nets_test.py
deeptables/tests/models/preprocessor_dask_test.py
deeptables/tests/models/preprocessor_test.py
deeptables/tests/models/run_dt.py
deeptables-0.2.6.dist-info/LICENSE
deeptables-0.2.6.dist-info/METADATA
deeptables-0.2.6.dist-info/WHEEL
deeptables-0.2.6.dist-info/top_level.txt
deeptables-0.2.6.dist-info/RECORD
