Metadata-Version: 2.1
Name: deeptables
Version: 0.2.6
Summary: Deep-learning Toolkit for Tabular datasets
Home-page: 
Author: DeepTables Community
Author-email: yangjian@zetyun.com
License: Apache License 2.0
Classifier: Operating System :: OS Independent
Classifier: Intended Audience :: Developers
Classifier: Intended Audience :: Education
Classifier: Intended Audience :: Science/Research
Classifier: Programming Language :: Python
Classifier: Programming Language :: Python :: 3.6
Classifier: Programming Language :: Python :: 3.7
Classifier: Programming Language :: Python :: 3.8
Classifier: Programming Language :: Python :: 3.9
Classifier: Topic :: Scientific/Engineering
Classifier: Topic :: Scientific/Engineering :: Artificial Intelligence
Classifier: Topic :: Software Development
Classifier: Topic :: Software Development :: Libraries
Classifier: Topic :: Software Development :: Libraries :: Python Modules
Requires-Python: >=3.6
License-File: LICENSE
Requires-Dist: packaging
Requires-Dist: scipy (>=1.3.1)
Requires-Dist: pandas (>=0.25.3)
Requires-Dist: numpy (>=1.16.5)
Requires-Dist: scikit-learn (>=0.22.1)
Requires-Dist: lightgbm (>=2.2.0)
Requires-Dist: category-encoders (>=2.1.0)
Requires-Dist: hypernets (>=0.3.0)
Requires-Dist: h5py (>=2.10.0)
Requires-Dist: eli5
Provides-Extra: tests
Requires-Dist: pytest ; extra == 'tests'
